sotfinder/__init__.py
sotfinder/astroalign.py
sotfinder/classes.py
sotfinder/plot.py
sotfinder/ransac.py
sotfinder/trajectory_extract.py
sotfinder-0.0.1.dist-info/LICENSE
sotfinder-0.0.1.dist-info/METADATA
sotfinder-0.0.1.dist-info/WHEEL
sotfinder-0.0.1.dist-info/top_level.txt
sotfinder-0.0.1.dist-info/RECORD
