Metadata-Version: 2.1
Name: sotfinder
Version: 0.0.1
Summary: SOTFINDER is an astrophotography analysis tool that expertly identifies and tracks space object trajectories in multi-frame images, while offering photometric analysis and dynamic visualization against a stellar backdrop.
Home-page: https://github.com/lcx366/SOTFINDER
Author: Chunxiao Li
Author-email: lcx366@126.com
License: MIT
Keywords: Astrometric Analysis,Trajectory Tracking,Photometric Measurement,Space Object Detection
Classifier: Development Status :: 4 - Beta
Classifier: Intended Audience :: Education
Classifier: Intended Audience :: Science/Research
Classifier: Programming Language :: Python :: 3.10
Classifier: Programming Language :: Python :: 3.11
Classifier: Programming Language :: Python :: 3.12
Classifier: License :: OSI Approved :: MIT License
Requires-Python: >=3.10
License-File: LICENSE
Requires-Dist: scipy
Requires-Dist: matplotlib
Requires-Dist: starextractor
Requires-Dist: scikit-learn
Requires-Dist: photutils
Requires-Dist: scikit-image
